clinicaltrials_interact/__init__.py
clinicaltrials_interact/clustering.py
clinicaltrials_interact/ctg_api.py
clinicaltrials_interact/navigation.py
clinicaltrials_interact-0.1.11.dist-info/METADATA
clinicaltrials_interact-0.1.11.dist-info/WHEEL
clinicaltrials_interact-0.1.11.dist-info/top_level.txt
clinicaltrials_interact-0.1.11.dist-info/RECORD
