Metadata-Version: 2.4
Name: clinicaltrials_interact
Version: 0.1.11
Summary: A Python package to interact with ClinicalTrials.gov API v2
Home-page: https://github.com/hsph-bst236/midterm-project-keyvulee-innovations/tree/main/clinicaltrials_interact
Author: KeyVuLee
License: MIT
Classifier: Programming Language :: Python :: 3
Classifier: License :: OSI Approved :: MIT License
Classifier: Operating System :: OS Independent
Requires-Python: >=3.6
Requires-Dist: requests<3.0.0,>=2.32.3
Requires-Dist: pandas<3.0.0,>=2.2.0
Requires-Dist: sentence-transformers<4.0.0,>=3.4.1
Requires-Dist: scikit-learn<2.0.0,>=1.6.1
Requires-Dist: matplotlib<4.0.0,>=3.10.1
Requires-Dist: seaborn<1.0.0,>=0.13.2
Requires-Dist: plotly>=5.0.0
Dynamic: author
Dynamic: classifier
Dynamic: description
Dynamic: description-content-type
Dynamic: home-page
Dynamic: license
Dynamic: requires-dist
Dynamic: requires-python
Dynamic: summary
